maite_datasets/__init__.py
maite_datasets/_base.py
maite_datasets/_bbox.py
maite_datasets/_builder.py
maite_datasets/_collate.py
maite_datasets/_fileio.py
maite_datasets/_reader.py
maite_datasets/_validate.py
maite_datasets/protocols.py
maite_datasets/py.typed
maite_datasets/adapters/__init__.py
maite_datasets/adapters/_huggingface.py
maite_datasets/image_classification/__init__.py
maite_datasets/image_classification/_cifar10.py
maite_datasets/image_classification/_mnist.py
maite_datasets/image_classification/_ships.py
maite_datasets/object_detection/__init__.py
maite_datasets/object_detection/_antiuav.py
maite_datasets/object_detection/_coco.py
maite_datasets/object_detection/_milco.py
maite_datasets/object_detection/_seadrone.py
maite_datasets/object_detection/_voc.py
maite_datasets/object_detection/_yolo.py
maite_datasets/wrappers/__init__.py
maite_datasets/wrappers/_torch.py
maite_datasets-0.0.9.dist-info/METADATA
maite_datasets-0.0.9.dist-info/WHEEL
maite_datasets-0.0.9.dist-info/licenses/LICENSE
maite_datasets-0.0.9.dist-info/RECORD
