Metadata-Version: 2.4
Name: maite-datasets
Version: 0.0.9
Summary: A collection of Image Classification and Object Detection task datasets conforming to the MAITE protocol.
Author-email: Andrew Weng <andrew.weng@ariacoustics.com>, Ryan Wood <ryan.wood@ariacoustics.com>, Shaun Jullens <shaun.jullens@ariacoustics.com>
License-Expression: MIT
License-File: LICENSE
Classifier: Development Status :: 4 - Beta
Classifier: Framework :: Pytest
Classifier: License :: OSI Approved :: MIT License
Classifier: Operating System :: OS Independent
Classifier: Programming Language :: Python :: 3 :: Only
Classifier: Programming Language :: Python :: 3.10
Classifier: Programming Language :: Python :: 3.11
Classifier: Programming Language :: Python :: 3.12
Classifier: Programming Language :: Python :: 3.13
Requires-Python: >=3.10
Requires-Dist: defusedxml>=0.7.1
Requires-Dist: maite<0.9,>=0.7
Requires-Dist: numpy>=1.24.2
Requires-Dist: pillow>=10.3.0
Requires-Dist: requests>=2.32.3
Requires-Dist: typing-extensions>=4.12
Provides-Extra: tqdm
Requires-Dist: tqdm>=4.66; extra == 'tqdm'
